django_szuprefix_saas/__init__.py
django_szuprefix_saas/comment/__init__.py
django_szuprefix_saas/comment/admin.py
django_szuprefix_saas/comment/apis.py
django_szuprefix_saas/comment/apps.py
django_szuprefix_saas/comment/helper.py
django_szuprefix_saas/comment/models.py
django_szuprefix_saas/comment/receivers.py
django_szuprefix_saas/comment/serializers.py
django_szuprefix_saas/comment/stats.py
django_szuprefix_saas/comment/migrations/0001_initial.py
django_szuprefix_saas/comment/migrations/0002_auto_20191013_2228.py
django_szuprefix_saas/comment/migrations/0003_auto_20191101_1652.py
django_szuprefix_saas/comment/migrations/0004_auto_20200106_1150.py
django_szuprefix_saas/comment/migrations/0005_rating.py
django_szuprefix_saas/comment/migrations/0006_auto_20200331_0355.py
django_szuprefix_saas/comment/migrations/0007_favorite.py
django_szuprefix_saas/comment/migrations/0008_auto_20200617_1558.py
django_szuprefix_saas/comment/migrations/0009_favorite_notes_count.py
django_szuprefix_saas/comment/migrations/0010_auto_20200708_1714.py
django_szuprefix_saas/comment/migrations/__init__.py
django_szuprefix_saas/company/__init__.py
django_szuprefix_saas/company/apps.py
django_szuprefix_saas/company/models.py
django_szuprefix_saas/course/__init__.py
django_szuprefix_saas/course/admin.py
django_szuprefix_saas/course/apis.py
django_szuprefix_saas/course/apps.py
django_szuprefix_saas/course/helper.py
django_szuprefix_saas/course/models.py
django_szuprefix_saas/course/receivers.py
django_szuprefix_saas/course/serializers.py
django_szuprefix_saas/course/stats.py
django_szuprefix_saas/course/migrations/0001_initial.py
django_szuprefix_saas/course/migrations/0002_auto_20180713_0629.py
django_szuprefix_saas/course/migrations/0003_auto_20180812_2146.py
django_szuprefix_saas/course/migrations/0004_auto_20180822_2359.py
django_szuprefix_saas/course/migrations/0005_auto_20190308_2010.py
django_szuprefix_saas/course/migrations/0006_auto_20190322_1214.py
django_szuprefix_saas-0.10.26.dist-info/METADATA
django_szuprefix_saas-0.10.26.dist-info/WHEEL
django_szuprefix_saas-0.10.26.dist-info/top_level.txt
django_szuprefix_saas-0.10.26.dist-info/RECORD
