Metadata-Version: 2.1
Name: django-szuprefix-saas
Version: 0.10.26
Summary: my saas in django
Home-page: https://github.com/szuprefix/django_szuprefix_saas
Author: Denis Huang
Author-email: szuprefix@126.com
License: MIT
Platform: UNKNOWN
Classifier: Environment :: Web Environment
Classifier: Intended Audience :: Developers
Classifier: Operating System :: OS Independent
Classifier: Topic :: Text Processing :: Indexing
Classifier: Topic :: Utilities
Classifier: Topic :: Internet
Classifier: Topic :: Software Development :: Libraries :: Python Modules
Classifier: Programming Language :: Python
Classifier: Programming Language :: Python :: 2
Classifier: Programming Language :: Python :: 2.7
Classifier: Programming Language :: Python :: 3
Requires-Dist: django-szuprefix (>=0.10.23)
Requires-Dist: unidecode
Requires-Dist: django-treebeard
Requires-Dist: rest-condition
Requires-Dist: sqlparse
Requires-Dist: xyz-qcloud (>=0.0.5)
